fast_prometheus/__init__.py
fast_prometheus/__version__.py
fast_prometheus/config.py
fast_prometheus/endpoint.py
fast_prometheus/exceptions.py
fast_prometheus/executor.py
fast_prometheus/factory.py
fast_prometheus/golden_signals.py
fast_prometheus/midlleware.py
fast_prometheus/py.typed
fast_prometheus/registry.py
fast_prometheus/saturation.py
fast_prometheus/types.py
fast_prometheus-0.1.0.dist-info/METADATA
fast_prometheus-0.1.0.dist-info/WHEEL
fast_prometheus-0.1.0.dist-info/entry_points.txt
fast_prometheus-0.1.0.dist-info/RECORD
