Metadata-Version: 2.4
Name: fast-prometheus
Version: 0.1.0
Summary: Prometheus metrics for projects on starlette, fastapi
Author-email: Vadim Shadrin <kod3852@gmail.com>
Requires-Python: >=3.10
Requires-Dist: prometheus-client>=0.21.1
Requires-Dist: psutil>=6.1.1
Requires-Dist: starlette>=0.37.2
